pychecked/__init__.py
pychecked/type_checking.py
pychecked-0.0.6.dist-info/DESCRIPTION.rst
pychecked-0.0.6.dist-info/METADATA
pychecked-0.0.6.dist-info/RECORD
pychecked-0.0.6.dist-info/WHEEL
pychecked-0.0.6.dist-info/metadata.json
pychecked-0.0.6.dist-info/top_level.txt
