Metadata-Version: 2.0
Name: pychecked
Version: 0.0.6
Summary: Python3+ type checking for annotated function signatures.
Home-page: https://github.com/a-tal/pychecked
Author: Adam Talsma
Author-email: adam@talsma.ca
License: BSD
Download-URL: https://github.com/a-tal/pychecked
Platform: UNKNOWN
Classifier: Development Status :: 5 - Production/Stable
Classifier: Intended Audience :: Developers
Classifier: License :: OSI Approved :: BSD License
Classifier: Programming Language :: Python
